{"desc": "• Super-Entspiegelung\r\n• Lotus-Effekt\r\n• extra gehärtet\r\n• dünne Kunststoffgläser\r\n• Tönung ohne Aufpreis", "headline": "Alles-Drin-Preis für Einstärkenbrille", "id": 1889, "img_s": "/media/thumbnails/qpons/brille24-alles-drin-preis-fuer-einstaerkenbrille_1_100.png?v=560744", "infotext": "", "online_from": "2012-10-20", "online_to": "2013-02-28", "resource_uri": "/api/v1/favoriteqpon/1889/", "retailer": "Brille24", "valid_from": "2012-10-20", "valid_to": "2013-02-28", "validity_text": "Jeweils zzgl. 5,- € Versand. Pro Person ein Gutschein einlösbar. Nicht auf reduzierte Brillen anwendbar."}